sr2p/__init__.py
sr2p/data/__init__.py
sr2p/data/normalization.py
sr2p/data/spatial_construction.py
sr2p/models/__init__.py
sr2p/models/base/__init__.py
sr2p/models/base/catboost.py
sr2p/models/base/dgat.py
sr2p/models/base/gat.py
sr2p/models/base/gnn_utils.py
sr2p/models/base/gs.py
sr2p/models/base/lightgbm.py
sr2p/models/base/pls.py
sr2p/models/base/xgboost.py
sr2p/models/meta/__init__.py
sr2p/models/meta/extratrees.py
sr2p/stacking/__init__.py
sr2p/stacking/base_learner.py
sr2p/stacking/base_learner_utils.py
sr2p/stacking/config.py
sr2p/stacking/meta_learner.py
sr2p/stacking/pipeline.py
sr2p-0.1.0.dist-info/licenses/LICENSE
sr2p-0.1.0.dist-info/METADATA
sr2p-0.1.0.dist-info/WHEEL
sr2p-0.1.0.dist-info/top_level.txt
sr2p-0.1.0.dist-info/RECORD
