Metadata-Version: 2.4
Name: sr2p
Version: 0.1.0
Summary: Spatial RNA to Protein prediction with stacking models
Author: Qingyue
License: MIT
Requires-Python: >=3.9
License-File: LICENSE
Requires-Dist: numpy>=1.24
Requires-Dist: pandas>=2.0
Requires-Dist: scikit-learn>=1.3
Requires-Dist: scipy>=1.10
Requires-Dist: joblib>=1.3
Provides-Extra: data
Requires-Dist: anndata>=0.10; extra == "data"
Requires-Dist: scanpy>=1.9; extra == "data"
Provides-Extra: boost
Requires-Dist: xgboost>=2.0; extra == "boost"
Requires-Dist: lightgbm>=4.0; extra == "boost"
Requires-Dist: catboost>=1.2; extra == "boost"
Provides-Extra: gnn
Requires-Dist: torch>=2.0; extra == "gnn"
Requires-Dist: torch-geometric>=2.5; extra == "gnn"
Requires-Dist: torch_scatter; extra == "gnn"
Requires-Dist: torch_sparse; extra == "gnn"
Requires-Dist: torch_cluster; extra == "gnn"
Requires-Dist: torch_spline_conv; extra == "gnn"
Provides-Extra: all
Requires-Dist: sr2p[boost,data,gnn]; extra == "all"
Dynamic: license-file
